{"pageContext":{"isCreatedByStatefulCreatePages":false,"id":"17612","display_address":"Medford City Hall, 85 George P. Hassett Drive, Medford, MA 02155","geocode_address":"85 George P Hassett Dr, Medford, MA 02155, USA","public_note":"","location_lng":-71.1057922,"location_lat":42.4181482,"client_location_name":"Medford Recreation","course_id":74654,"is_full":0,"start_date":"2019-07-29","end_date":"2019-08-02","course_type_long_description":"Prepare for a full-day LEGO® camp packed with hands-on and minds-on STEM fun! Build projects inspired by cool machines close to home such as Trains, Helicopters, Treehouses, and Beam Bridges. Then build X-Wings, Energy Catapults, and Defense Turrets from a galaxy far, far away! Learn about BOTH kinds of The Force in this new full-day themed engineering camp for LEGO® fanatics!","course_type_name":"STEM + Jedi w/ LEGO® Materials: FULL DAY","course_type_group":"Basic Lego","age_range_start":5,"age_range_end":8,"age_range_display":"Ages 5 - 8","date_time_display":"Jul 29th - Aug 2nd, 2019 : 9:00 am - 4:00 pm","category_group_name":"Camp","days_of_the_week":"Mon-Fri","omit_dates":null,"room":null,"course_web_publishing_action_type_id":"2","action_url":"https://medfordma.myrec.com/info/activities/default.aspx?type=activities","is_restricted_registration":"0","email_registration_description":null,"phone_registration_description":null,"action_url_comment":"Search Medford Rec's online registration system using keyword \"LEGO\"","course_web_publishing_action_type":"Register.Client","action_type":"register","action_url_external":true}}