{"pageContext":{"isCreatedByStatefulCreatePages":false,"id":"5512","display_address":"159 North Cullen Ave, Glendora, CA 91741","geocode_address":"159 North Cullen Avenue, Glendora, CA 91741, USA","public_note":"For more info or to be contacted automatically when registration begins, please contact Michael Luong at Michael@play-well.org, or call (424) 672-5496.","location_lng":-117.860549,"location_lat":34.137614,"client_location_name":"Legion Building","course_id":77400,"is_full":0,"start_date":"2019-07-15","end_date":"2019-07-19","course_type_long_description":"The Force Awakens in this introductory engineering course for young Jedi!  Explore engineering principles by designing and building projects using LEGO® materials such as X-Wings, R2 Units, Energy Catapults, Defense Turrets, and Settlements from a galaxy far, far away. Create motorized and architectural projects with imagination and engineering to defeat the Empire!","course_type_name":"Jedi Engineering with LEGO® Materials","course_type_group":"Star Wars","age_range_start":5,"age_range_end":7,"age_range_display":"Ages 5 - 7","date_time_display":"Jul 15th - Jul 19th, 2019 : 10:00 am - 1:00 pm","category_group_name":"Camp","days_of_the_week":"Mon-Fri","omit_dates":null,"room":"Main Hall","course_web_publishing_action_type_id":"2","action_url":"https://apm.activecommunities.com/glendoracommsvcs/","is_restricted_registration":"0","email_registration_description":null,"phone_registration_description":"(626) 914-8228","action_url_comment":"Registration begins May 17th, 2018. For more info or help registering, please e-mail Michael@play-well.org","course_web_publishing_action_type":"Register.Client","action_type":"register","action_url_external":true}}