{"pageContext":{"isCreatedByStatefulCreatePages":false,"id":"17015","display_address":"177 Estoria Street, Atlanta, GA 30316","geocode_address":"177 Estoria St SE, Atlanta, GA 30316, USA","public_note":"LEGO Engineering Camp is under \"School Age Camps\" on the GPCP website.","location_lng":-84.3636237,"location_lat":33.7496846,"client_location_name":"Grant Park Cooperative PS-Cabbagetown","course_id":77200,"is_full":0,"start_date":"2019-07-15","end_date":"2019-07-19","course_type_long_description":"Level up your engineering skills with Play-Well TEKnologies and tens of thousands of LEGO® parts! Apply real-world concepts in physics, engineering, and architecture through engineer-designed projects such as: Gear Cars, Castles, Airplanes, and Scissor Lifts. Design and build as never before, and explore your craziest ideas in a supportive environment. There are no prerequisites for this course.","course_type_name":"STEM FUNdamentals, Summer 19","course_type_group":"Basic Lego","age_range_start":5,"age_range_end":8,"age_range_display":"Ages 5 - 8","date_time_display":"Jul 15th - Jul 19th, 2019 : 9:00 am - 12:00 pm","category_group_name":"Camp","days_of_the_week":"Mon-Fri","omit_dates":null,"room":null,"course_web_publishing_action_type_id":"2","action_url":"http://gpcp.org/info/108741","is_restricted_registration":"0","email_registration_description":null,"phone_registration_description":null,"action_url_comment":"LEGO Engineering Camp is under \"School Age Camps\" on the GPCP website.","course_web_publishing_action_type":"Register.Client","action_type":"register","action_url_external":true}}