{"pageContext":{"isCreatedByStatefulCreatePages":false,"id":"3232","display_address":"17910 E Parkside Drive North, Commerce City, CO 80022","geocode_address":"17910 Parkside Drive North, Commerce City, CO 80022, USA","public_note":"","location_lng":-104.7810375,"location_lat":39.8900439,"client_location_name":"Reunion Recreation Center","course_id":75499,"is_full":0,"start_date":"2019-07-22","end_date":"2019-07-25","course_type_long_description":"Build and program robots in this introductory Robotics class using the LEGO速 WeDo速 system.  Learn basic programming skills, simple engineering concepts, and the names of robot components.  Work in small groups to complete several projects using tilt and motion sensors.  This is a great way to prepare young Robotics enthusiasts for our more advanced Robotics programs","course_type_name":"Robotics using the LEGO速 WeDo速 System","course_type_group":"Lego Robotics","age_range_start":7,"age_range_end":8,"age_range_display":"Ages 7 - 8","date_time_display":"Jul 22nd - Jul 25th, 2019 : 9:00 am - 12:00 pm","category_group_name":"Camp","days_of_the_week":"Monday, Tuesday and Thursday","omit_dates":null,"room":"Conference Room","course_web_publishing_action_type_id":"2","action_url":"http://www.reunionmetro.org","is_restricted_registration":"0","email_registration_description":null,"phone_registration_description":"303-288-5431","action_url_comment":"Click on Recreation Programs and Look for Play-Well Camps","course_web_publishing_action_type":"Register.Client","action_type":"register","action_url_external":true}}