{"pageContext":{"isCreatedByStatefulCreatePages":false,"id":"17311","display_address":"9565 Highland Dr., Sandy, UT 84092","geocode_address":"9565 Highland Dr, Sandy, UT 84092, USA","public_note":"","location_lng":-111.8335921,"location_lat":40.5774175,"client_location_name":"Alta Canyon Sports Center","course_id":74373,"is_full":0,"start_date":"2019-07-29","end_date":"2019-08-02","course_type_long_description":"The Force Awakens in this introductory engineering course for young Jedi!  Explore engineering principles by designing and building projects using LEGO® materials such as X-Wings, R2 Units, Energy Catapults, Defense Turrets, and Settlements from a galaxy far, far away. Create motorized and architectural projects with imagination and engineering to defeat the Empire!","course_type_name":"Jedi Engineering with LEGO® Materials","course_type_group":"Star Wars","age_range_start":5,"age_range_end":7,"age_range_display":"Ages 5 - 7","date_time_display":"Jul 29th - Aug 2nd, 2019 : 9:00 am - 12:00 pm","category_group_name":"Camp","days_of_the_week":"Mon-Fri","omit_dates":null,"room":null,"course_web_publishing_action_type_id":"2","action_url":"https://sandy.utah.gov/departments/parks-and-recreation/alta-canyon-sports-center/summer-camp-programs","is_restricted_registration":"0","email_registration_description":null,"phone_registration_description":"(801) 568-4600","action_url_comment":"Register online, at the front desk, or by calling (801) 568-4600","course_web_publishing_action_type":"Register.Client","action_type":"register","action_url_external":true}}