{"pageContext":{"isCreatedByStatefulCreatePages":false,"id":"16380","display_address":"University Place, 201 S Estes Dr., Chapel Hill, NC 27514","geocode_address":"201 S Estes Dr, Chapel Hill, NC 27514, USA","public_note":"","location_lng":-79.0268783,"location_lat":35.9278462,"client_location_name":"Kidzu Children's Museum","course_id":79183,"is_full":0,"start_date":"2019-08-19","end_date":"2019-08-23","course_type_long_description":"Level up your engineering skills with Play-Well TEKnologies and tens of thousands of LEGO® parts! Apply real-world concepts in physics, engineering, and architecture through engineer-designed projects such as: Gear Cars, Gondolas, Merry-Go-Rounds, and Scissor Lifts. Design and build as never before, and explore your craziest ideas in a supportive environment. There are no prerequisites for this course.","course_type_name":"STEM Explorations, 2019 Summer","course_type_group":"Basic Lego","age_range_start":6,"age_range_end":10,"age_range_display":"Ages 6 - 10","date_time_display":"Aug 19th - Aug 23rd, 2019 : 9:00 am - 2:00 pm","category_group_name":"Camp","days_of_the_week":"Mon-Fri","omit_dates":null,"room":"TBA","course_web_publishing_action_type_id":"2","action_url":"https://www.kidzuchildrensmuseum.org/project/playwell-lego-summer-camp/","is_restricted_registration":"0","email_registration_description":null,"phone_registration_description":null,"action_url_comment":null,"course_web_publishing_action_type":"Register.Client","action_type":"register","action_url_external":true}}